dbt/adapters/upsolver/__init__.py
dbt/adapters/upsolver/__version__.py
dbt/adapters/upsolver/connections.py
dbt/adapters/upsolver/impl.py
dbt/adapters/upsolver/relation.py
dbt/adapters/upsolver/options/connection_options.py
dbt/adapters/upsolver/options/copy_options.py
dbt/adapters/upsolver/options/geterate_options_docs.py
dbt/adapters/upsolver/options/target_options.py
dbt/adapters/upsolver/options/transformation_options.py
dbt/include/upsolver/__init__.py
dbt/include/upsolver/dbt_project.yml
dbt/include/upsolver/profile_template.yml
dbt/include/upsolver/macros/adapters.sql
dbt/include/upsolver/macros/catalog.sql
dbt/include/upsolver/macros/materializations/connection.sql
dbt/include/upsolver/macros/materializations/materializedview.sql
dbt/include/upsolver/macros/materializations/incremental/create_copy_job.sql
dbt/include/upsolver/macros/materializations/incremental/create_insert_job.sql
dbt/include/upsolver/macros/materializations/incremental/create_merge_job.sql
dbt/include/upsolver/macros/materializations/incremental/incremental.sql
dbt/include/upsolver/macros/materializations/utils/alter_job.sql
dbt/include/upsolver/macros/materializations/utils/create_table.sql
dbt/include/upsolver/macros/materializations/utils/expextations.sql
dbt/include/upsolver/macros/materializations/utils/render_options.sql
dbt_upsolver-1.5.29.dist-info/LICENSE
dbt_upsolver-1.5.29.dist-info/METADATA
dbt_upsolver-1.5.29.dist-info/WHEEL
dbt_upsolver-1.5.29.dist-info/top_level.txt
dbt_upsolver-1.5.29.dist-info/RECORD
