Metadata-Version: 2.1
Name: dbt-upsolver
Version: 1.5.29
Summary: The Upsolver adapter plugin for dbt
Home-page: https://github.com/tanyshak/dbt-upsolver
Author: Upsolver Team
Author-email: info@upsolver.com
License: MIT
Classifier: Development Status :: 5 - Production/Stable
Classifier: License :: OSI Approved :: Apache Software License
Classifier: Operating System :: Microsoft :: Windows
Classifier: Operating System :: MacOS :: MacOS X
Classifier: Operating System :: POSIX :: Linux
Classifier: Programming Language :: Python :: 3.7
Classifier: Programming Language :: Python :: 3.8
Classifier: Programming Language :: Python :: 3.9
Classifier: Programming Language :: Python :: 3.10
Classifier: Programming Language :: Python :: 3.11
Requires-Python: >=3.7
License-File: LICENSE
Requires-Dist: dbt-core ~=1.5.0
Requires-Dist: upsolver-sdk-python
